Workbook

Sheet Budget
A1: Department | B1: Month | C1: Budget
A2: Sales | B2: Jan | C2: 50000
A3: Marketing | B3: Jan | C3: 40000
A4: HR | B4: Jan | C4: 15000
A5: IT | B5: Jan | C5: 30000
A6: Finance | B6: Jan | C6: 20000
A7: Sales | B7: Feb | C7: 52000
A8: Marketing | B8: Feb | C8: 41000
A9: HR | B9: Feb | C9: 15000
A10: IT | B10: Feb | C10: 30000
A11: Finance | B11: Feb | C11: 20000
A12: Sales | B12: Mar | C12: 51000
A13: Marketing | B13: Mar | C13: 42000
... A61: Finance | B61: Dec | C61: 26000
C62: =SUM(C2:C61) -> 2087000

Sheet Expenses
A1: Date | B1: Department | C1: Category | D1: Amount
A2: 46024 | B2: Sales | C2: Travel | D2: 7000
A3: 46025 | B3: Marketing | C3: Advertising | D3: 12000
A4: 46026 | B4: HR | C4: Recruitment | D4: 3000
A5: 46027 | B5: IT | C5: Software | D5: 8000
A6: 46028 | B6: Finance | C6: Office Supplies | D6: 2000
A7: 46032 | B7: Sales | C7: Client Meeting | D7: 5000
A8: 46034 | B8: Marketing | C8: Social Media | D8: 9000
A9: 46037 | B9: IT | C9: Hardware | D9: 12000
A10: 46040 | B10: HR | C10: Training | D10: 4000
A11: 46042 | B11: Finance | C11: Audit | D11: 6000
A12: 46056 | B12: Sales | C12: Travel | D12: 6500
A13: 46058 | B13: Marketing | C13: Advertising | D13: 13000
... A51: 46172 | B51: Finance | C51: Audit | D51: 6800
D52: =SUM(D2:D51) -> 362700

Sheet Revenue
A1: Product | B1: Month | C1: Revenue | D1: Cost
A2: Product A | B2: Jan | C2: 120000 | D2: 70000
A3: Product B | B3: Jan | C3: 80000 | D3: 60000
A4: Product C | B4: Jan | C4: 150000 | D4: 90000
A5: Product D | B5: Jan | C5: 60000 | D5: 55000
A6: Product E | B6: Jan | C6: 100000 | D6: 65000
A7: Product A | B7: Feb | C7: 125000 | D7: 72000
A8: Product B | B8: Feb | C8: 82000 | D8: 61000
A9: Product C | B9: Feb | C9: 152000 | D9: 91000
A10: Product D | B10: Feb | C10: 62000 | D10: 56000
A11: Product E | B11: Feb | C11: 102000 | D11: 66000
A12: Product A | B12: Mar | C12: 128000 | D12: 73000
A13: Product B | B13: Mar | C13: 85000 | D13: 62000
... A61: Product E | B61: Dec | C61: 128000 | D61: 76000
C62: =SUM(C2:C61) -> 6887000 | D62: =SUM(D2:D61) -> 4448000

Sheet KPI
A1: KPI | B1: Value
A2: Total Budget | B2: 2087000
A3: Total Expenses | B3: 362700
A4: Total Revenue | B4: 6887000
A5: Total Cost | B5: 4448000
A6: Total Profit | B6: =B4 - B5 -> 2439000
A7: Budget Utilization (%) | B7: =(B3/B2)*100 -> 17.379013
A8: Contribution Margin (%) | B8: =(B6/B4)*100 -> 35.414549
A9: Burn Rate | B9: =B3/12 -> 30225

Sheet Variance
A1: Department | B1: Total Budget | C1: Total Expenses | D1: Variance | E1: Variance % | F1: Status
A2: Sales | B2: =SUMIF(Budget!A:A,A2,Budget!C:C) -> 667000 | C2: =SUMIF(Expenses!B:B,A2,Expenses!D:D) -> 61800 | D2: =B2-C2 -> 605200 | E2: =D2/B2 -> 0.90734633 | F2: =IF(D2<0,"Over Budget","Within Budget") -> Within Budget
A3: Marketing | B3: =SUMIF(Budget!A:A,A3,Budget!C:C) -> 547000 | C3: =SUMIF(Expenses!B:B,A3,Expenses!D:D) -> 117300 | D3: =B3-C3 -> 429700 | E3: =D3/B3 -> 0.78555759 | F3: =IF(D3<0,"Over Budget","Within Budget") -> Within Budget
A4: HR | B4: =SUMIF(Budget!A:A,A4,Budget!C:C) -> 211000 | C4: =SUMIF(Expenses!B:B,A4,Expenses!D:D) -> 40400 | D4: =B4-C4 -> 170600 | E4: =D4/B4 -> 0.80853081 | F4: =IF(D4<0,"Over Budget","Within Budget") -> Within Budget
A5: IT | B5: =SUMIF(Budget!A:A,A5,Budget!C:C) -> 391000 | C5: =SUMIF(Expenses!B:B,A5,Expenses!D:D) -> 101300 | D5: =B5-C5 -> 289700 | E5: =D5/B5 -> 0.74092072 | F5: =IF(D5<0,"Over Budget","Within Budget") -> Within Budget
A6: Finance | B6: =SUMIF(Budget!A:A,A6,Budget!C:C) -> 271000 | C6: =SUMIF(Expenses!B:B,A6,Expenses!D:D) -> 41900 | D6: =B6-C6 -> 229100 | E6: =D6/B6 -> 0.84538745 | F6: =IF(D6<0,"Over Budget","Within Budget") -> Within Budget

Sheet Profitability
A1: Product | B1: Total Revenue | C1: Total Cost | D1: Profit | E1: Profit Margin %
A2: Product A | B2: =SUMIF(Revenue!A:A,A2,Revenue!C:C) -> 1633000 | C2: =SUMIF(Revenue!A:A,A2,Revenue!D:D) -> 927000 | D2: =B2-C2 -> 706000 | E2: =D2/B2 -> 0.43233313
A3: Product B | B3: =SUMIF(Revenue!A:A,A3,Revenue!C:C) -> 1095000 | C3: =SUMIF(Revenue!A:A,A3,Revenue!D:D) -> 786000 | D3: =B3-C3 -> 309000 | E3: =D3/B3 -> 0.28219178
A4: Product C | B4: =SUMIF(Revenue!A:A,A4,Revenue!C:C) -> 1965000 | C4: =SUMIF(Revenue!A:A,A4,Revenue!D:D) -> 1163000 | D4: =B4-C4 -> 802000 | E4: =D4/B4 -> 0.40814249
A5: Product D | B5: =SUMIF(Revenue!A:A,A5,Revenue!C:C) -> 829000 | C5: =SUMIF(Revenue!A:A,A5,Revenue!D:D) -> 726000 | D5: =B5-C5 -> 103000 | E5: =D5/B5 -> 0.12424608
A6: Product E | B6: =SUMIF(Revenue!A:A,A6,Revenue!C:C) -> 1365000 | C6: =SUMIF(Revenue!A:A,A6,Revenue!D:D) -> 846000 | D6: =B6-C6 -> 519000 | E6: =D6/B6 -> 0.38021978

Sheet Dashboard
A1: FinInsight - Expense Control & Profitability Dashboard
A4: Total Budget | C4: Total Expences | E4: Total Revenue | G4: Total Profit
A5: =KPI!B2 -> 2087000 | C5: =KPI!B3 -> 362700 | E5: =KPI!B4 -> 6887000 | G5: =KPI!B6 -> 2439000
